{
"id": "JOB_build_graph_data_25abfde2-b051-4f46-b905-5ba6b75a0ebc",
"task_id": "TASK_build_graph_data_553f38c4-2467-46da-b78f-003ad6c7d73f",
"status": "<Status.SKIPPED: 8>",
"status_change_records": {
"SUBMITTED": "2025-04-26T19:09:25.685944",
"PENDING": "2025-04-26T19:09:25.804613",
"SKIPPED": "2025-04-26T19:09:26.031680"
},
"force": false,
"submit_id": "SUBMISSION_39bc70e6-bd3b-4832-85a0-6fe530a9e4b3",
"submit_entity_id": "SCENARIO_scenario_95cbe037-9d4a-4871-bf81-5c193941e23b",
"creation_date": "2025-04-26T19:09:25.685944",
"subscribers": [
{
"fct_name": "_Orchestrator._update_submission_status",
"fct_params": [],
"fct_module": "taipy.core._orchestrator._orchestrator"
},
{
"fct_name": "_Orchestrator._on_status_change",
"fct_params": [],
"fct_module": "taipy.core._orchestrator._orchestrator"
}
],
"stacktrace": [],
"version": "d07db358-857e-4aaf-bcf0-13ecbcb73825"
}